README
setup.py
test/test_compile.py
tiddlywebplugins/__init__.py
tiddlywebplugins/jsondispatcher.py
tiddlywebplugins.jsondispatcher.egg-info/PKG-INFO
tiddlywebplugins.jsondispatcher.egg-info/SOURCES.txt
tiddlywebplugins.jsondispatcher.egg-info/dependency_links.txt
tiddlywebplugins.jsondispatcher.egg-info/namespace_packages.txt
tiddlywebplugins.jsondispatcher.egg-info/not-zip-safe
tiddlywebplugins.jsondispatcher.egg-info/requires.txt
tiddlywebplugins.jsondispatcher.egg-info/top_level.txt