Metadata-Version: 1.0
Name: tiddlywebplugins.jsondispatcher
Version: 0.1.2
Summary: A TiddlyWeb plugin to allow the dispatching of tiddlers to non-Python handlers by serialising tiddler data to JSON
Home-page: http://pypi.python.org/pypi/tiddlywebplugins.jsondispatcher
Author: Ben Paddock
Author-email: pads@thisispads.me.uk
License: UNKNOWN
Platform: Posix; MacOS X; Windows
